nrel_sup3r-0.2.5.dist-info/licenses/LICENSE
sup3r/__init__.py
sup3r/_version.py
sup3r/cli.py
sup3r/batch/__init__.py
sup3r/batch/batch_cli.py
sup3r/bias/__init__.py
sup3r/bias/abstract.py
sup3r/bias/base.py
sup3r/bias/bias_calc.py
sup3r/bias/bias_calc_cli.py
sup3r/bias/bias_calc_vortex.py
sup3r/bias/bias_transforms.py
sup3r/bias/mixins.py
sup3r/bias/presrat.py
sup3r/bias/qdm.py
sup3r/bias/utilities.py
sup3r/configs/spatial/README.rst
sup3r/configs/spatial/disc.json
sup3r/configs/spatial/gen_10x_2f.json
sup3r/configs/spatial/gen_2x_1f.json
sup3r/configs/spatial/gen_2x_2f.json
sup3r/configs/spatiotemporal/README.rst
sup3r/configs/spatiotemporal/disc.json
sup3r/configs/spatiotemporal/gen_2x_12x_14f.json
sup3r/configs/spatiotemporal/gen_2x_2x_2f.json
sup3r/configs/spatiotemporal/gen_3x_4x_10f.json
sup3r/configs/spatiotemporal/gen_3x_4x_14f.json
sup3r/configs/spatiotemporal/gen_3x_4x_1f.json
sup3r/configs/spatiotemporal/gen_3x_4x_2f.json
sup3r/configs/spatiotemporal/gen_4x_24x_3f.json
sup3r/configs/sup3rcc/README.rst
sup3r/configs/sup3rcc/gen_solar_1x_8x_1f.json
sup3r/configs/sup3rcc/gen_solar_5x_1x_1f.json
sup3r/configs/sup3rcc/gen_trh_1x_24x_2f.json
sup3r/configs/sup3rcc/gen_wind_1x_24x_6f.json
sup3r/configs/sup3rcc/gen_wind_3x_4x_2f.json
sup3r/configs/sup3rcc/gen_wind_5x_1x_6f.json
sup3r/models/__init__.py
sup3r/models/abstract.py
sup3r/models/base.py
sup3r/models/conditional.py
sup3r/models/dc.py
sup3r/models/interface.py
sup3r/models/linear.py
sup3r/models/multi_step.py
sup3r/models/solar_cc.py
sup3r/models/surface.py
sup3r/models/utilities.py
sup3r/models/with_obs.py
sup3r/pipeline/__init__.py
sup3r/pipeline/forward_pass.py
sup3r/pipeline/forward_pass_cli.py
sup3r/pipeline/pipeline_cli.py
sup3r/pipeline/slicer.py
sup3r/pipeline/strategy.py
sup3r/pipeline/utilities.py
sup3r/postprocessing/__init__.py
sup3r/postprocessing/data_collect_cli.py
sup3r/postprocessing/collectors/__init__.py
sup3r/postprocessing/collectors/base.py
sup3r/postprocessing/collectors/h5.py
sup3r/postprocessing/collectors/nc.py
nrel_sup3r-0.2.5.dist-info/METADATA
nrel_sup3r-0.2.5.dist-info/WHEEL
nrel_sup3r-0.2.5.dist-info/entry_points.txt
nrel_sup3r-0.2.5.dist-info/top_level.txt
nrel_sup3r-0.2.5.dist-info/RECORD
