Metadata-Version: 2.4
Name: NREL-sup3r
Version: 0.2.5
Summary: Super Resolving Renewable Resource Data (sup3r)
Author-email: Brandon Benton <brandon.benton@nrel.gov>
License: BSD-3-Clause
Project-URL: homepage, https://github.com/NREL/sup3r
Project-URL: documentation, https://nrel.github.io/sup3r/
Project-URL: repository, https://github.com/NREL/sup3r
Keywords: sup3r,NREL
Classifier: Development Status :: 4 - Beta
Classifier: Intended Audience :: Science/Research
Classifier: License :: OSI Approved :: BSD License
Classifier: Natural Language :: English
Classifier: Programming Language :: Python :: 3.9
Classifier: Programming Language :: Python :: 3.10
Classifier: Programming Language :: Python :: 3.11
Requires-Python: >=3.9
License-File: LICENSE
Requires-Dist: NREL-rex>=0.2.91
Requires-Dist: NREL-phygnn>=0.0.32
Requires-Dist: NREL-gaps>=0.6.13
Requires-Dist: NREL-farms>=1.0.4
Requires-Dist: dask>=2022.0
Requires-Dist: netCDF4<1.7,>=1.5.8
Requires-Dist: h5netcdf>=1.1.0
Requires-Dist: cftime>=1.6.2
Requires-Dist: matplotlib>=3.1
Requires-Dist: numpy<2.0.0,>=1.7.0
Requires-Dist: pandas>=2.0
Requires-Dist: pillow>=10.0
Requires-Dist: pytest>=5.2
Requires-Dist: scipy>=1.0.0
Requires-Dist: sphinx>=7.0
Requires-Dist: xarray>=2023.0
Provides-Extra: dev
Requires-Dist: build>=0.5; extra == "dev"
Requires-Dist: flake8; extra == "dev"
Requires-Dist: pre-commit; extra == "dev"
Requires-Dist: pylint; extra == "dev"
Provides-Extra: doc
Requires-Dist: sphinx>=7.0; extra == "doc"
Requires-Dist: sphinx-click>=4.0; extra == "doc"
Requires-Dist: sphinx-book-theme>=1.1.1; extra == "doc"
Requires-Dist: sphinx_autosummary_accessors>=2023.4.0; extra == "doc"
Provides-Extra: test
Requires-Dist: pytest>=5.2; extra == "test"
Requires-Dist: pytest-env; extra == "test"
Provides-Extra: build
Requires-Dist: build<2,>=1.2.2; extra == "build"
Requires-Dist: pkginfo<2,>=1.10.0; extra == "build"
Requires-Dist: twine<7,>=6.1.0; extra == "build"
Dynamic: license-file
